{
    "@context": "https://linked.art/ns/v1/linked-art.json",
    "brought_into_existence_by": {
        "id": "http://data.okeeffemuseum.org/person/1577/birthevent/",
        "timespan": {
            "begin_of_the_begin": "1908-01-01T00:00:00",
            "end_of_the_end": "1908-01-01T00:00:00",
            "id": "http://data.okeeffemuseum.org/person/1577/birthevent/timespan/",
            "label": "1908",
            "type": "TimeSpan"
        },
        "type": "BeginningOfExistence"
    },
    "classified_as": [
        {
            "id": "aat:300025969",
            "label": "corporations",
            "type": "Type"
        }
    ],
    "exact_match": [
        "ulan:500312843"
    ],
    "id": "http://data.okeeffemuseum.org/person/1577",
    "identified_by": [
        {
            "classified_as": [
                {
                    "id": "aat:300404670",
                    "label": "preferred terms",
                    "type": "Type"
                }
            ],
            "id": "http://data.okeeffemuseum.org/person/1577/name/0",
            "type": "Name",
            "value": "University of British Columbia"
        },
        {
            "classified_as": [
                {
                    "id": "aat:300404621",
                    "label": "repository numbers",
                    "type": "Type"
                }
            ],
            "id": "http://data.okeeffemuseum.org/person/1577/identifier/1/",
            "type": "Identifier",
            "value": "1577"
        }
    ],
    "label": "University of British Columbia",
    "member_of": [
        {
            "id": "http://data.okeeffemuseum.org/person/1577/nationality/",
            "label": "Canadian",
            "type": "Group"
        },
        {
            "id": "http://data.okeeffemuseum.org/person/1577/occupation/",
            "label": "Art Museum",
            "type": "Group"
        }
    ],
    "participated_in": [
        {
            "classified_as": [
                {
                    "id": "aat:300263369",
                    "label": "occupations",
                    "type": "Type"
                }
            ],
            "id": "http://data.okeeffemuseum.org/occupation/art-museum",
            "label": "Art Museum",
            "type": "Activity"
        }
    ],
    "referred_to_by": [
        {
            "classified_as": [
                {
                    "id": "aat:300080102",
                    "label": "biographies",
                    "type": "Type"
                }
            ],
            "id": "http://data.okeeffemuseum.org/person/1577/description/",
            "label": "The University of British Columbia (UBC) is a public research university with campuses near Vancouver and in Kelowna, British Columbia. Established in 1908, it is British Columbia's oldest university. The university ranks among the top three universities in Canada. With an annual research budget of $759 million, UBC funds over 8,000 projects a year.The Vancouver campus is situated adjacent to the University Endowment Lands located about 10 km (6 mi) west of downtown Vancouver. UBC is home to TRIUMF, Canada's national laboratory for particle and nuclear physics, which houses the world's largest cyclotron. In addition to the Peter Wall Institute for Advanced Studies and Stuart Blusson Quantum Matter Institute, UBC and the Max Planck Society collectively established the first Max Planck Institute in North America, specializing in quantum materials. One of the largest research libraries in Canada, the UBC Library system has over 10 million volumes among its 21 branches. The Okanagan campus, acquired in 2005, is located in Kelowna, British Columbia. ^ ^Eight Nobel laureates, 74 Rhodes scholars, 65 Olympians garnering medals, ten fellows in both American Academy of Arts & Sciences and the Royal Society, and 273 fellows to the Royal Society of Canada have been affiliated with UBC. Three Canadian prime ministers, including Canada's first female prime minister, Kim Campbell, and current prime minister, Justin Trudeau, have been educated at UBC. (Sourced from Wikipedia May 2023)",
            "type": "LinguisticObject"
        }
    ],
    "type": "Actor"
}