{
    "@context": "https://linked.art/ns/v1/linked-art.json",
    "about": [
        {
            "label": "Exhibition catalogs",
            "type": "Type"
        },
        {
            "label": "Exhibition catalogs",
            "type": "Type"
        }
    ],
    "classified_as": [
        {
            "id": "aat:300028051",
            "label": "books",
            "type": "Type"
        }
    ],
    "crm:P104_is_subject_to": null,
    "crm:P57_has_number_of_parts": null,
    "current_keeper": null,
    "current_owner": null,
    "custody_transferred_through": [],
    "depicts": [],
    "id": "http://data.okeeffemuseum.org/library/13129",
    "identified_by": [
        {
            "classified_as": [
                {
                    "id": "aat:300311706",
                    "label": "call numbers",
                    "type": "Type"
                }
            ],
            "id": "http://data.okeeffemuseum.org/library/13129/050",
            "type": "Identifier",
            "value": "ND1042 .L765"
        },
        {
            "classified_as": [
                {
                    "id": "aat:300404670",
                    "label": "preferred terms",
                    "type": "Type"
                }
            ],
            "type": "Name",
            "value": "Kung Hsien and the Nanking school: some Chinese paintings of the seventeenth century, a loan exhibition [March 17-April 16, 1955, China House, New York City]."
        },
        {
            "classified_as": [
                {
                    "id": "aat:300404670",
                    "label": "preferred terms",
                    "type": "Type"
                }
            ],
            "type": "Name",
            "value": "Kung Hsien and the Nanking school: some Chinese paintings of the seventeenth century, a loan exhibition [March 17-April 16, 1955, China House, New York City]."
        }
    ],
    "label": null,
    "made_of": [],
    "ore:isAggregatedBy": null,
    "part_of": [],
    "produced_by": {
        "carried_out_by": [
            {
                "id": "http://data.okeeffemuseum.org/person/lippe-aschwin-",
                "identified_by": [
                    {
                        "classified_as": [
                            {
                                "id": "aat:300404670",
                                "label": "preferred terms",
                                "type": "Type"
                            }
                        ],
                        "id": "http://data.okeeffemuseum.org/person/lippe-aschwin-/name",
                        "type": "Name",
                        "value": "Lippe, Aschwin."
                    }
                ],
                "type": "Actor"
            }
        ],
        "consists_of": [
            {
                "carried_out_by": [
                    {
                        "classified_as": [],
                        "id": "http://data.okeeffemuseum.org/person/chinese-art-society-of-america",
                        "identified_by": [
                            {
                                "classified_as": [
                                    {
                                        "id": "aat:300404670",
                                        "label": "preferred terms",
                                        "type": "Type"
                                    }
                                ],
                                "id": "http://data.okeeffemuseum.org/person/chinese-art-society-of-america/name",
                                "type": "Name",
                                "value": "Chinese Art Society of America"
                            }
                        ],
                        "type": "Actor"
                    }
                ],
                "classified_as": [],
                "id": "http://data.okeeffemuseum.org/library/13129/production/publishing",
                "technique": [
                    {
                        "id": "relators:pbl",
                        "label": "Publisher",
                        "type": "Type"
                    }
                ],
                "type": "Production"
            },
            {
                "carried_out_by": [
                    {
                        "classified_as": [],
                        "id": "http://data.okeeffemuseum.org/person/lippe-aschwin-",
                        "identified_by": [
                            {
                                "classified_as": [
                                    {
                                        "id": "aat:300404670",
                                        "label": "preferred terms",
                                        "type": "Type"
                                    }
                                ],
                                "id": "http://data.okeeffemuseum.org/person/lippe-aschwin-/name",
                                "type": "Name",
                                "value": "Lippe, Aschwin."
                            }
                        ],
                        "type": "Actor"
                    }
                ],
                "classified_as": [],
                "id": "http://data.okeeffemuseum.org/library/13129/production/author",
                "technique": [
                    {
                        "id": "relators:aut",
                        "label": "Author",
                        "type": "Type"
                    }
                ],
                "type": "Production"
            }
        ],
        "id": "http://data.okeeffemuseum.org/library/13129/production",
        "timespan": {
            "begin_of_the_begin": "1955-01-01T00:00:00",
            "end_of_the_end": "1955-01-01T00:00:00",
            "id": "http://data.okeeffemuseum.org/library/13129/production/timespan",
            "label": "1955",
            "type": "TimeSpan"
        },
        "type": "Production"
    },
    "referred_to_by": [
        {
            "classified_as": [
                {
                    "id": "aat:300028702",
                    "label": "inscriptions",
                    "type": "Type"
                }
            ],
            "id": "http://data.okeeffemuseum.org/library/13129/590a",
            "type": "LinguisticObject",
            "value": "abq copy : good condition.|SColl abq : Embossed stamp on cover : Georgia O'Keeffe / Abiquiu, New Mexico."
        },
        {
            "classified_as": [
                {
                    "id": "aat:300411780",
                    "label": "descriptions",
                    "type": "Type"
                }
            ],
            "id": "http://data.okeeffemuseum.org/library/13129/500a",
            "type": "LinguisticObject",
            "value": "Georgia O'Keeffe Personal Library.<br>Cover title."
        },
        {
            "classified_as": [
                {
                    "id": "aat:300266038",
                    "label": "format",
                    "type": "Type"
                }
            ],
            "id": "http://data.okeeffemuseum.org/library/13129/300abc",
            "type": "LinguisticObject",
            "value": "10 pages, [4] pages of plates : illustrations ; 23 cm."
        }
    ],
    "refers_to": [],
    "related": [],
    "representation": [],
    "specific_technique": [],
    "subject_of": [],
    "type": "ManMadeObject",
    "used_for": []
}