{
    "@context": "https://linked.art/ns/v1/linked-art.json",
    "aggregated_by": [
        {
            "aggregates": [
                "http://data.okeeffemuseum.org/object/8643",
                "http://data.okeeffemuseum.org/object/8289",
                "http://data.okeeffemuseum.org/object/8747",
                "http://data.okeeffemuseum.org/object/8482",
                "http://data.okeeffemuseum.org/object/8705",
                "http://data.okeeffemuseum.org/object/8645",
                "http://data.okeeffemuseum.org/object/8257"
            ],
            "classified_as": [
                "relationships:exhibition",
                "aat:300417473"
            ],
            "id": "http://data.okeeffemuseum.org/exhibition/1006/aggregation",
            "label": "Roots of Abstract Art in America",
            "related": [
                {
                    "id": "http://data.okeeffemuseum.org/exhibition/1006/timespan",
                    "label": "1965 - 1966",
                    "type": "TimeSpan"
                },
                {
                    "id": "http://data.okeeffemuseum.org/person/404",
                    "label": "Smithsonian American Art Museum",
                    "type": "Group"
                }
            ],
            "type": "Aggregation"
        },
        {
            "aggregates": [
                "http://data.okeeffemuseum.org/object/8830",
                "http://data.okeeffemuseum.org/object/8683",
                "http://data.okeeffemuseum.org/object/123",
                "http://data.okeeffemuseum.org/object/8822",
                "http://data.okeeffemuseum.org/object/8707",
                "http://data.okeeffemuseum.org/object/8410",
                "http://data.okeeffemuseum.org/object/8724",
                "http://data.okeeffemuseum.org/object/8828",
                "http://data.okeeffemuseum.org/object/8647",
                "http://data.okeeffemuseum.org/object/8705",
                "http://data.okeeffemuseum.org/object/8586",
                "http://data.okeeffemuseum.org/object/567",
                "http://data.okeeffemuseum.org/object/8702",
                "http://data.okeeffemuseum.org/object/79",
                "http://data.okeeffemuseum.org/object/8659",
                "http://data.okeeffemuseum.org/object/8402",
                "http://data.okeeffemuseum.org/object/145",
                "http://data.okeeffemuseum.org/object/57",
                "http://data.okeeffemuseum.org/object/8763",
                "http://data.okeeffemuseum.org/object/8832",
                "http://data.okeeffemuseum.org/object/8502",
                "http://data.okeeffemuseum.org/object/8831",
                "http://data.okeeffemuseum.org/object/8811",
                "http://data.okeeffemuseum.org/object/3",
                "http://data.okeeffemuseum.org/object/8812",
                "http://data.okeeffemuseum.org/object/8829",
                "http://data.okeeffemuseum.org/object/124",
                "http://data.okeeffemuseum.org/object/8557",
                "http://data.okeeffemuseum.org/object/71"
            ],
            "classified_as": [
                "aat:300417473",
                "relationships:exhibition"
            ],
            "id": "http://data.okeeffemuseum.org/exhibition/249/aggregation",
            "label": "Georgia O'Keeffe: Exhibition of Paintings (1919--1934)",
            "related": [
                {
                    "id": "http://data.okeeffemuseum.org/person/1476",
                    "label": "An American Place",
                    "type": "Group"
                },
                {
                    "id": "http://data.okeeffemuseum.org/exhibition/249/timespan",
                    "label": "1935 - 1935",
                    "type": "TimeSpan"
                }
            ],
            "type": "Aggregation"
        },
        {
            "aggregates": [
                "http://data.okeeffemuseum.org/object/8860",
                "http://data.okeeffemuseum.org/object/565"
            ],
            "classified_as": [
                "relationships:exhibition",
                "aat:300417473"
            ],
            "id": "http://data.okeeffemuseum.org/exhibition/958/aggregation",
            "label": "Art Since 1889: An Exhibition Presented in Celebration of the 75th Anniversary of the Founding of the University of New Mexico",
            "related": [
                {
                    "id": "http://data.okeeffemuseum.org/exhibition/958/timespan",
                    "label": "1964 - 1964",
                    "type": "TimeSpan"
                },
                {
                    "id": "http://data.okeeffemuseum.org/person/1399",
                    "label": "University of New Mexico Art Museum",
                    "type": "Group"
                }
            ],
            "type": "Aggregation"
        },
        {
            "aggregates": [
                "http://data.okeeffemuseum.org/object/8339"
            ],
            "classified_as": [
                "aat:300417473",
                "relationships:exhibition"
            ],
            "id": "http://data.okeeffemuseum.org/exhibition/986/aggregation",
            "label": "Boston Collect Modern Art",
            "related": [
                {
                    "id": "http://data.okeeffemuseum.org/exhibition/986/timespan",
                    "label": "1964 - 1964",
                    "type": "TimeSpan"
                },
                {
                    "id": "http://data.okeeffemuseum.org/person/1736",
                    "label": "Brandeis University",
                    "type": "Group"
                }
            ],
            "type": "Aggregation"
        },
        {
            "aggregates": [
                "http://data.okeeffemuseum.org/object/8840",
                "http://data.okeeffemuseum.org/object/8693",
                "http://data.okeeffemuseum.org/object/8696",
                "http://data.okeeffemuseum.org/object/8681",
                "http://data.okeeffemuseum.org/object/8760",
                "http://data.okeeffemuseum.org/object/8888",
                "http://data.okeeffemuseum.org/object/8882",
                "http://data.okeeffemuseum.org/object/8540",
                "http://data.okeeffemuseum.org/object/8762",
                "http://data.okeeffemuseum.org/object/8731",
                "http://data.okeeffemuseum.org/object/8682",
                "http://data.okeeffemuseum.org/object/8764",
                "http://data.okeeffemuseum.org/object/8823",
                "http://data.okeeffemuseum.org/object/8759",
                "http://data.okeeffemuseum.org/object/8533",
                "http://data.okeeffemuseum.org/object/8564",
                "http://data.okeeffemuseum.org/object/1009",
                "http://data.okeeffemuseum.org/object/8763",
                "http://data.okeeffemuseum.org/object/8705",
                "http://data.okeeffemuseum.org/object/8852",
                "http://data.okeeffemuseum.org/object/8925",
                "http://data.okeeffemuseum.org/object/10155",
                "http://data.okeeffemuseum.org/object/8672",
                "http://data.okeeffemuseum.org/object/8901",
                "http://data.okeeffemuseum.org/object/1028",
                "http://data.okeeffemuseum.org/object/8915"
            ],
            "classified_as": [
                "aat:300417473",
                "relationships:exhibition"
            ],
            "id": "http://data.okeeffemuseum.org/exhibition/565/aggregation",
            "label": "An Exhibition of Paintings by Georgia O'Keeffe",
            "related": [
                {
                    "id": "http://data.okeeffemuseum.org/person/1629",
                    "label": "Mayo Hill Galleries",
                    "type": "Group"
                },
                {
                    "id": "http://data.okeeffemuseum.org/exhibition/565/timespan",
                    "label": "1953 - 1953",
                    "type": "TimeSpan"
                }
            ],
            "type": "Aggregation"
        },
        {
            "aggregates": [
                "http://data.okeeffemuseum.org/object/323",
                "http://data.okeeffemuseum.org/object/8775"
            ],
            "classified_as": [
                "aat:300417473",
                "relationships:exhibition"
            ],
            "id": "http://data.okeeffemuseum.org/exhibition/495/aggregation",
            "label": "Contemporary Painting From the Addison Gallery, Adover",
            "related": [
                {
                    "id": "http://data.okeeffemuseum.org/exhibition/495/timespan",
                    "label": "1950 - 1950",
                    "type": "TimeSpan"
                },
                {
                    "id": "http://data.okeeffemuseum.org/person/1581",
                    "label": "Institute of Contemporary Art",
                    "type": "Group"
                }
            ],
            "type": "Aggregation"
        },
        {
            "aggregates": [
                "http://data.okeeffemuseum.org/object/9437"
            ],
            "classified_as": [
                "aat:300417473",
                "relationships:exhibition"
            ],
            "id": "http://data.okeeffemuseum.org/exhibition/505/aggregation",
            "label": "Amerikanische Malerei: Werden and Gegenwart",
            "related": [
                {
                    "id": "http://data.okeeffemuseum.org/person/1598",
                    "label": "Berliner Festwochen (Rathaus Sch\u00f6neberg",
                    "type": "Group"
                },
                {
                    "id": "http://data.okeeffemuseum.org/exhibition/505/timespan",
                    "label": "1951 - 1951",
                    "type": "TimeSpan"
                }
            ],
            "type": "Aggregation"
        },
        {
            "aggregates": [
                "http://data.okeeffemuseum.org/object/8935",
                "http://data.okeeffemuseum.org/object/8540",
                "http://data.okeeffemuseum.org/object/8707",
                "http://data.okeeffemuseum.org/object/8818",
                "http://data.okeeffemuseum.org/object/8731",
                "http://data.okeeffemuseum.org/object/8606",
                "http://data.okeeffemuseum.org/object/8596",
                "http://data.okeeffemuseum.org/object/8623",
                "http://data.okeeffemuseum.org/object/8446",
                "http://data.okeeffemuseum.org/object/154",
                "http://data.okeeffemuseum.org/object/8958",
                "http://data.okeeffemuseum.org/object/8466",
                "http://data.okeeffemuseum.org/object/8386",
                "http://data.okeeffemuseum.org/object/8586",
                "http://data.okeeffemuseum.org/object/9164",
                "http://data.okeeffemuseum.org/object/8653",
                "http://data.okeeffemuseum.org/object/8906",
                "http://data.okeeffemuseum.org/object/8790",
                "http://data.okeeffemuseum.org/object/8713",
                "http://data.okeeffemuseum.org/object/8705",
                "http://data.okeeffemuseum.org/object/8711",
                "http://data.okeeffemuseum.org/object/8664",
                "http://data.okeeffemuseum.org/object/8604"
            ],
            "classified_as": [
                "aat:300417473",
                "relationships:exhibition"
            ],
            "id": "http://data.okeeffemuseum.org/exhibition/1152/aggregation",
            "label": "Georgia O'Keeffe",
            "related": [
                {
                    "id": "http://data.okeeffemuseum.org/exhibition/1152/timespan",
                    "label": "1984 - 1984",
                    "type": "TimeSpan"
                },
                {
                    "id": "http://data.okeeffemuseum.org/person/1709",
                    "label": "Madison Museum of Contemporary Art",
                    "type": "Group"
                }
            ],
            "type": "Aggregation"
        },
        {
            "aggregates": [
                "http://data.okeeffemuseum.org/object/8477",
                "http://data.okeeffemuseum.org/object/8697",
                "http://data.okeeffemuseum.org/object/8705",
                "http://data.okeeffemuseum.org/object/8694",
                "http://data.okeeffemuseum.org/object/8700",
                "http://data.okeeffemuseum.org/object/8647",
                "http://data.okeeffemuseum.org/object/8685",
                "http://data.okeeffemuseum.org/object/8701",
                "http://data.okeeffemuseum.org/object/8698",
                "http://data.okeeffemuseum.org/object/8595",
                "http://data.okeeffemuseum.org/object/8703",
                "http://data.okeeffemuseum.org/object/8709",
                "http://data.okeeffemuseum.org/object/72",
                "http://data.okeeffemuseum.org/object/8691",
                "http://data.okeeffemuseum.org/object/8688",
                "http://data.okeeffemuseum.org/object/6",
                "http://data.okeeffemuseum.org/object/8596",
                "http://data.okeeffemuseum.org/object/8681",
                "http://data.okeeffemuseum.org/object/8687",
                "http://data.okeeffemuseum.org/object/8702",
                "http://data.okeeffemuseum.org/object/8686",
                "http://data.okeeffemuseum.org/object/8679",
                "http://data.okeeffemuseum.org/object/8682",
                "http://data.okeeffemuseum.org/object/8693",
                "http://data.okeeffemuseum.org/object/8710",
                "http://data.okeeffemuseum.org/object/8683",
                "http://data.okeeffemuseum.org/object/8699",
                "http://data.okeeffemuseum.org/object/8696"
            ],
            "classified_as": [
                "relationships:exhibition",
                "aat:300417473"
            ],
            "id": "http://data.okeeffemuseum.org/exhibition/184/aggregation",
            "label": "Georgia O'Keeffe Paintings, 1928",
            "related": [
                {
                    "id": "http://data.okeeffemuseum.org/person/1324",
                    "label": "Intimate Gallery",
                    "type": "Group"
                },
                {
                    "id": "http://data.okeeffemuseum.org/exhibition/184/timespan",
                    "label": "1929 - 1929",
                    "type": "TimeSpan"
                }
            ],
            "type": "Aggregation"
        },
        {
            "aggregates": [
                "http://data.okeeffemuseum.org/object/8764",
                "http://data.okeeffemuseum.org/object/8901",
                "http://data.okeeffemuseum.org/object/8762",
                "http://data.okeeffemuseum.org/object/8564",
                "http://data.okeeffemuseum.org/object/547",
                "http://data.okeeffemuseum.org/object/8823",
                "http://data.okeeffemuseum.org/object/10165",
                "http://data.okeeffemuseum.org/object/8763",
                "http://data.okeeffemuseum.org/object/8888",
                "http://data.okeeffemuseum.org/object/10152",
                "http://data.okeeffemuseum.org/object/8693",
                "http://data.okeeffemuseum.org/object/8915",
                "http://data.okeeffemuseum.org/object/10158",
                "http://data.okeeffemuseum.org/object/8705",
                "http://data.okeeffemuseum.org/object/8682",
                "http://data.okeeffemuseum.org/object/8759",
                "http://data.okeeffemuseum.org/object/9437",
                "http://data.okeeffemuseum.org/object/562",
                "http://data.okeeffemuseum.org/object/10259",
                "http://data.okeeffemuseum.org/object/8681",
                "http://data.okeeffemuseum.org/object/8696",
                "http://data.okeeffemuseum.org/object/8731",
                "http://data.okeeffemuseum.org/object/8533",
                "http://data.okeeffemuseum.org/object/8760",
                "http://data.okeeffemuseum.org/object/8852",
                "http://data.okeeffemuseum.org/object/8925",
                "http://data.okeeffemuseum.org/object/8540",
                "http://data.okeeffemuseum.org/object/8882",
                "http://data.okeeffemuseum.org/object/1009",
                "http://data.okeeffemuseum.org/object/10148",
                "http://data.okeeffemuseum.org/object/8840",
                "http://data.okeeffemuseum.org/object/8672",
                "http://data.okeeffemuseum.org/object/1028"
            ],
            "classified_as": [
                "relationships:exhibition",
                "aat:300417473"
            ],
            "id": "http://data.okeeffemuseum.org/exhibition/564/aggregation",
            "label": "An Exhibition of Paintings by Georgia O'Keeffe",
            "related": [
                {
                    "id": "http://data.okeeffemuseum.org/exhibition/564/timespan",
                    "label": "1953 - 1953",
                    "type": "TimeSpan"
                },
                {
                    "id": "http://data.okeeffemuseum.org/person/353",
                    "label": "Dallas Museum of Art",
                    "type": "Group"
                }
            ],
            "type": "Aggregation"
        },
        {
            "aggregates": [
                "http://data.okeeffemuseum.org/object/10180",
                "http://data.okeeffemuseum.org/object/10366",
                "http://data.okeeffemuseum.org/object/8925",
                "http://data.okeeffemuseum.org/object/10151",
                "http://data.okeeffemuseum.org/object/8672",
                "http://data.okeeffemuseum.org/object/7419",
                "http://data.okeeffemuseum.org/object/8493",
                "http://data.okeeffemuseum.org/object/8540",
                "http://data.okeeffemuseum.org/object/9437",
                "http://data.okeeffemuseum.org/object/8705"
            ],
            "classified_as": [
                "relationships:exhibition",
                "aat:300417473"
            ],
            "id": "http://data.okeeffemuseum.org/exhibition/562/aggregation",
            "label": "Georgia O'Keeffe Retrospective Exhibition",
            "related": [
                {
                    "id": "http://data.okeeffemuseum.org/exhibition/562/timespan",
                    "label": "1952 - 1952",
                    "type": "TimeSpan"
                },
                {
                    "id": "http://data.okeeffemuseum.org/person/1626",
                    "label": "Philbrook Museum of Art",
                    "type": "Group"
                }
            ],
            "type": "Aggregation"
        }
    ],
    "id": "http://data.okeeffemuseum.org/object/8705",
    "type": "ManMadeObject"
}