{
    "@context": "https://linked.art/ns/v1/linked-art.json",
    "aggregated_by": [
        {
            "aggregates": [
                "http://data.okeeffemuseum.org/object/8659",
                "http://data.okeeffemuseum.org/object/10184",
                "http://data.okeeffemuseum.org/object/584",
                "http://data.okeeffemuseum.org/object/35",
                "http://data.okeeffemuseum.org/object/8896",
                "http://data.okeeffemuseum.org/object/8789",
                "http://data.okeeffemuseum.org/object/1036",
                "http://data.okeeffemuseum.org/object/8777",
                "http://data.okeeffemuseum.org/object/8642",
                "http://data.okeeffemuseum.org/object/8874",
                "http://data.okeeffemuseum.org/object/8596",
                "http://data.okeeffemuseum.org/object/8595",
                "http://data.okeeffemuseum.org/object/8801",
                "http://data.okeeffemuseum.org/object/40",
                "http://data.okeeffemuseum.org/object/8590",
                "http://data.okeeffemuseum.org/object/1218",
                "http://data.okeeffemuseum.org/object/10356",
                "http://data.okeeffemuseum.org/object/8876",
                "http://data.okeeffemuseum.org/object/10357"
            ],
            "classified_as": [
                "relationships:exhibition",
                "aat:300417473"
            ],
            "id": "http://data.okeeffemuseum.org/exhibition/1164/aggregation",
            "label": "Georgia O'Keeffe: Paintings",
            "related": [
                {
                    "id": "http://data.okeeffemuseum.org/person/728",
                    "label": "New Mexico Museum of Art",
                    "type": "Group"
                },
                {
                    "id": "http://data.okeeffemuseum.org/exhibition/1164/timespan",
                    "label": "1986 - 1987",
                    "type": "TimeSpan"
                }
            ],
            "type": "Aggregation"
        }
    ],
    "id": "http://data.okeeffemuseum.org/object/9457",
    "type": "ManMadeObject"
}