{
    "@context": "http://iiif.io/api/presentation/2/context.json",
    "@id": "https://iiif.okeeffemuseum.org/presentation/622.json",
    "@type": "sc:Manifest",
    "label": "Georgia O'Keeffe. Untitled (Still-Life), 1916-1917. Pen and black ink on paper, 3 1/2 x 2 1/2 inches. Georgia O'Keeffe Museum. Gift of The Georgia O'Keeffe Foundation. \u00a9 Georgia O'Keeffe Museum. [2006.5.63]",
    "metadata": [
        {
            "label": "Caption",
            "value": "Georgia O'Keeffe. Untitled (Still-Life), 1916-1917. Pen and black ink on paper, 3 1/2 x 2 1/2 inches. Georgia O'Keeffe Museum. Gift of The Georgia O'Keeffe Foundation. \u00a9 Georgia O'Keeffe Museum. [2006.5.63]"
        }
    ],
    "sequences": [
        {
            "@type": "sc:Sequence",
            "canvases": [
                {
                    "@id": "https://iiif.okeeffemuseum.org/presentation/canvas/786478.json",
                    "@type": "sc:Canvas",
                    "height": 3342,
                    "images": [
                        {
                            "@type": "oa:Annotation",
                            "motivation": "sc:painting",
                            "on": "https://iiif.okeeffemuseum.org/presentation/canvas/786478.json",
                            "resource": {
                                "@id": "https://iiif.okeeffemuseum.org/image/iiif/2/786478/full/full/0/default.jpg",
                                "@type": "dctypes:Image",
                                "format": "image/jpeg",
                                "service": {
                                    "@context": "http://iiif.io/api/image/2/context.json",
                                    "@id": "https://iiif.okeeffemuseum.org/image/iiif/2/786478",
                                    "profile": "http://iiif.io/api/image/2/level2.json"
                                }
                            }
                        }
                    ],
                    "label": "786478",
                    "width": 2718
                }
            ]
        }
    ],
    "viewingDirection": "left-to-right"
}