{
    "@context": "http://iiif.io/api/presentation/2/context.json",
    "@id": "https://iiif.okeeffemuseum.org/presentation/93.json",
    "@type": "sc:Manifest",
    "label": "Georgia O'Keeffe. Winter Cottonwoods East V, 1954. Oil on canvas, 40 x 36 1/16 inches. Georgia O'Keeffe Museum. Gift of The Burnett Foundation. \u00a9 Georgia O'Keeffe Museum. [1997.6.24]",
    "metadata": [
        {
            "label": "Caption",
            "value": "Georgia O'Keeffe. Winter Cottonwoods East V, 1954. Oil on canvas, 40 x 36 1/16 inches. Georgia O'Keeffe Museum. Gift of The Burnett Foundation. \u00a9 Georgia O'Keeffe Museum. [1997.6.24]"
        }
    ],
    "sequences": [
        {
            "@type": "sc:Sequence",
            "canvases": [
                {
                    "@id": "https://iiif.okeeffemuseum.org/presentation/canvas/786543.json",
                    "@type": "sc:Canvas",
                    "height": 11361,
                    "images": [
                        {
                            "@type": "oa:Annotation",
                            "motivation": "sc:painting",
                            "on": "https://iiif.okeeffemuseum.org/presentation/canvas/786543.json",
                            "resource": {
                                "@id": "https://iiif.okeeffemuseum.org/image/iiif/2/786543/full/full/0/default.jpg",
                                "@type": "dctypes:Image",
                                "format": "image/jpeg",
                                "service": {
                                    "@context": "http://iiif.io/api/image/2/context.json",
                                    "@id": "https://iiif.okeeffemuseum.org/image/iiif/2/786543",
                                    "profile": "http://iiif.io/api/image/2/level2.json"
                                }
                            }
                        }
                    ],
                    "label": "786543",
                    "width": 10244
                }
            ]
        }
    ],
    "viewingDirection": "left-to-right"
}