{
    "@context": "https://linked.art/ns/v1/linked-art.json",
    "carried_out_by": [
        {
            "id": "http://data.okeeffemuseum.org/person/1641",
            "identified_by": [
                {
                    "classified_as": [
                        "aat:300404670"
                    ],
                    "id": "http://data.okeeffemuseum.org/person/1641/name/0",
                    "type": "Name",
                    "value": "Staten Island Museum"
                }
            ],
            "type": "Actor"
        }
    ],
    "classified_as": [
        "aat:300054766"
    ],
    "consists_of": [
        {
            "carried_out_by": [
                {
                    "id": "http://data.okeeffemuseum.org/person/1641",
                    "identified_by": [
                        {
                            "classified_as": [
                                "aat:300404670"
                            ],
                            "id": "http://data.okeeffemuseum.org/person/1641/name/0",
                            "type": "Name",
                            "value": "Staten Island Museum"
                        }
                    ],
                    "type": "Actor"
                }
            ],
            "id": "http://data.okeeffemuseum.org/exhibition/621",
            "timespan": {
                "begin_of_the_begin": "1955-11-27T00:00:00",
                "end_of_the_end": "1956-01-10T00:00:00",
                "id": "http://data.okeeffemuseum.org/exhibition/621/timespan",
                "type": "TimeSpan"
            },
            "took_place_at": [
                {
                    "id": "http://data.okeeffemuseum.org/place/venue/staten-island-new-york",
                    "identified_by": [
                        {
                            "classified_as": [
                                "aat:300404670"
                            ],
                            "id": "http://data.okeeffemuseum.org/place/venue/staten-island-new-york/name",
                            "type": "Name",
                            "value": "Staten Island/New York"
                        }
                    ],
                    "type": "Place"
                }
            ],
            "type": "Activity",
            "used_specific_object": [
                "http://data.okeeffemuseum.org/object/8622",
                "http://data.okeeffemuseum.org/object/8659"
            ]
        }
    ],
    "id": "http://data.okeeffemuseum.org/touring-exhibition/414",
    "identified_by": [
        {
            "classified_as": [
                "aat:300404670"
            ],
            "id": "http://data.okeeffemuseum.org/touring-exhibition/414/title",
            "type": "Name",
            "value": "Modern Realism"
        }
    ],
    "label": "Modern Realism",
    "referred_to_by": [
        {
            "classified_as": [
                "aat:300411780"
            ],
            "id": "http://data.okeeffemuseum.org/touring-exhibition/414/description",
            "type": "LinguisticObject",
            "value": "1955 \nStaten Island, New York \nStaten Island Museum \nModern Realism \n27 November 1955-January 1956"
        }
    ],
    "timespan": {
        "begin_of_the_begin": "1955-11-27T00:00:00",
        "end_of_the_end": "1956-01-10T00:00:00",
        "id": "http://data.okeeffemuseum.org/touring-exhibition/414/timespan",
        "type": "TimeSpan"
    },
    "type": "Activity",
    "used_specific_object": [
        "http://data.okeeffemuseum.org/object/8622",
        "http://data.okeeffemuseum.org/object/8659"
    ]
}