{
    "@context": "https://linked.art/ns/v1/linked-art.json",
    "aggregated_by": [
        {
            "aggregates": [
                "http://data.okeeffemuseum.org/library/7646",
                "http://data.okeeffemuseum.org/library/7561",
                "http://data.okeeffemuseum.org/library/12866",
                "http://data.okeeffemuseum.org/library/12719"
            ],
            "classified_as": [
                "aat:300417473",
                "relationships:roles"
            ],
            "id": "http://data.okeeffemuseum.org/person/garden-city-pub-co-/relationships/http:/id.loc.gov/vocabulary/relators/pbl",
            "related": [
                {
                    "id": "relators:pbl",
                    "label": "Publisher",
                    "type": "Type"
                }
            ],
            "type": "Aggregation"
        }
    ],
    "id": "http://data.okeeffemuseum.org/person/garden-city-pub-co-",
    "type": "Actor"
}